LICENSE
MANIFEST.in
README.rst
nastran_pch_reader.py
setup.py
nastran_pch_reader.egg-info/PKG-INFO
nastran_pch_reader.egg-info/SOURCES.txt
nastran_pch_reader.egg-info/dependency_links.txt
nastran_pch_reader.egg-info/not-zip-safe
nastran_pch_reader.egg-info/top_level.txt