Metadata-Version: 1.1
Name: nastran-pch-reader
Version: 1.0.2
Summary: NASTRAN punch file parser
Home-page: https://github.com/anick107/nastran_pch_reader
Author: Nikolay Asmolovskiy
Author-email: nick.asmolovsky@gmail.com
License: BSD
Platform: UNKNOWN
Classifier: Programming Language :: Python :: 3
Classifier: Intended Audience :: Other Audience
Classifier: License :: OSI Approved :: BSD License
Classifier: Topic :: Software Development :: Libraries
Classifier: Topic :: Utilities
Classifier: Topic :: Text Processing
